{"2024_04_android_qq_file_storage_path.md":"mak2BPOj","2024_04_browser_ua_value.md":"DAa28D1P","2024_04_former_doctor_who.md":"D6xFkGou","2024_04_git_branch.md":"BIT3kGpv","2024_04_git_cli.md":"ClwQHzNJ","2024_04_gpg_communication.md":"BtDjyoQx","2024_04_modern_cryptography.md":"CxFwpoZ3","2024_04_obsidian_shortcut_key.md":"XsfTVCQV","2024_04_qqmail_third_party_config.md":"ejNMko9i","2024_04_remove_file_from_git_history.md":"73tKMCqK","2024_04_use_ffmpeg.md":"CFHLwlC4","2024_04_use_latex.md":"BO101eAj","2024_04_use_regex.md":"BnvzFe-6","2024_04_use_vim.md":"Etd4IcaQ","2024_04_use_vscode.md":"CvEp_Y64","2024_05_vscode_snippets_variable.md":"DEmXyVD9","2024_06_git_commit_message_standard.md":"BIdcvTay","2024_06_readme_outline.md":"0sVyaX5K","2024_07_gen_gpg_key.md":"CicJvauN","2024_07_git-crypt_official_doc.md":"BGT6JWAL","2024_07_git-crypt_official_doc_zh.md":"hlfkRpA6","2024_07_use_git-crypt.md":"C_OOgk24","2024_08_bilibili_embedding_code.md":"qjb-9KJM","2024_08_personal_software.md":"RebZZRRg","2024_08_use_you-get.md":"CPSTIqb2","2024_09_git_force_overwrite_local_repo.md":"BObg8xTz","2024_10_deploy_github_page.md":"BXPYY1K8","2024_10_use_git-izer.md":"CfOgoVwq","2024_10_use_lazy.nvim.md":"Dxw0PHat","2024_10_use_linux.md":"Bde9UWsh","2024_10_use_openssl_encrypt.md":"DsmoXQXm","2024_10_use_python.md":"DfTwyed2","2024_10_use_vitepress.md":"CEwDiJ_4","2024_10_windows_delete_right_click_menu.md":"BhJ-8bSb","categories.md":"Cxzj1Mwd","index.md":"NzCUFgV5","tags.md":"CNdyNSbe"}
